.long-description.html
README.rst
setup.py
src/collective/__init__.py
src/collective.cropimage.egg-info/PKG-INFO
src/collective.cropimage.egg-info/SOURCES.txt
src/collective.cropimage.egg-info/dependency_links.txt
src/collective.cropimage.egg-info/entry_points.txt
src/collective.cropimage.egg-info/namespace_packages.txt
src/collective.cropimage.egg-info/not-zip-safe
src/collective.cropimage.egg-info/requires.txt
src/collective.cropimage.egg-info/top_level.txt
src/collective/cropimage/__init__.py
src/collective/cropimage/configure.zcml
src/collective/cropimage/id.py
src/collective/cropimage/interfaces.py
src/collective/cropimage/upgrades.py
src/collective/cropimage/upgrades.zcml
src/collective/cropimage/browser/__init__.py
src/collective/cropimage/browser/configure.zcml
src/collective/cropimage/browser/interfaces.py
src/collective/cropimage/browser/miscellaneous.py
src/collective/cropimage/browser/template.py
src/collective/cropimage/browser/javascripts/jquery.Jcrop.js
src/collective/cropimage/browser/stylesheets/Jcrop.gif
src/collective/cropimage/browser/stylesheets/main.css
src/collective/cropimage/browser/templates/controlpanel.pt
src/collective/cropimage/browser/templates/crop_image.pt
src/collective/cropimage/docs/CREDITS.rst
src/collective/cropimage/docs/HISTORY.rst
src/collective/cropimage/docs/LICENSE.rst
src/collective/cropimage/locales/collective.cropimage.pot
src/collective/cropimage/locales/fi/LC_MESSAGES/collective.cropimage.mo
src/collective/cropimage/locales/fi/LC_MESSAGES/collective.cropimage.po
src/collective/cropimage/profiles/default/actions.xml
src/collective/cropimage/profiles/default/browserlayer.xml
src/collective/cropimage/profiles/default/controlpanel.xml
src/collective/cropimage/profiles/default/cssregistry.xml
src/collective/cropimage/profiles/default/jsregistry.xml
src/collective/cropimage/profiles/default/metadata.xml
src/collective/cropimage/profiles/default/registry.xml
src/collective/cropimage/profiles/uninstall/registry.xml
src/collective/cropimage/tests/__init__.py
src/collective/cropimage/tests/base.py
src/collective/cropimage/tests/test_CropImageIDControlPanelForm.py
src/collective/cropimage/tests/test_CropImageView.py
src/collective/cropimage/tests/test_IAddID.py
src/collective/cropimage/tests/test_ID.py
src/collective/cropimage/tests/test_IID.py
src/collective/cropimage/tests/test_Miscellaneous.py
