Metadata-Version: 1.1
Name: collective.cropimage
Version: 1.6
Summary: Store cropped image dimension for farther usage.
Home-page: https://github.com/collective/collective.cropimage/
Author: Taito Horiuchi
Author-email: taito.horiuchi@gmail.com
License: BSD
Platform: UNKNOWN
Classifier: Framework :: Plone
Classifier: Framework :: Plone :: 4.3
Classifier: License :: OSI Approved :: BSD License
Classifier: Programming Language :: Python
Classifier: Programming Language :: Python :: 2.7
